parsers/json/__init__.py
parsers/json/json_functions.py
parsers/json/json_parser.py
parsers/src/__init__.py
parsers/src/constants.py
parsers/src/general_serialize_functions.py
parsers/xml/__init__.py
parsers/xml/xml_functions.py
parsers/xml/xml_parser.py
my_serializer-1.42.dist-info/METADATA
my_serializer-1.42.dist-info/WHEEL
my_serializer-1.42.dist-info/top_level.txt
my_serializer-1.42.dist-info/RECORD
