Metadata-Version: 2.1
Name: my-serializer
Version: 1.42
Summary: Library for serialization/deserialization of objects in python(json, xml)
Home-page: https://github.com/SergeyBrykulskii/IGI_Labs/tree/Lab3/Lab3
Author: Sergey Brykulskii
Author-email: serxio6758@gmail.com
Classifier: Intended Audience :: Developers
Classifier: Programming Language :: Python :: 3.10
Classifier: Operating System :: OS Independent
